turvallisuusneuvonta/__init__.py
turvallisuusneuvonta/__main__.py
turvallisuusneuvonta/cli.py
turvallisuusneuvonta/turvallisuusneuvonta.py
turvallisuusneuvonta/csaf/__init__.py
turvallisuusneuvonta/csaf/csaf.py
turvallisuusneuvonta/csaf/definitions.py
turvallisuusneuvonta/csaf/document.py
turvallisuusneuvonta/csaf/product.py
turvallisuusneuvonta/csaf/vulnerability.py
turvallisuusneuvonta/csaf/core/__init__.py
turvallisuusneuvonta/csaf/core/rules/__init__.py
turvallisuusneuvonta/csaf/core/rules/mandatory/__init__.py
turvallisuusneuvonta/csaf/core/rules/mandatory/acyclic_product_ids.py
turvallisuusneuvonta/csaf/core/rules/mandatory/consistent_product_status.py
turvallisuusneuvonta/csaf/core/rules/mandatory/defined_group_ids.py
turvallisuusneuvonta/csaf/core/rules/mandatory/defined_product_ids.py
turvallisuusneuvonta/csaf/core/rules/mandatory/mandatory.py
turvallisuusneuvonta/csaf/core/rules/mandatory/translator_and_source_lang.py
turvallisuusneuvonta/csaf/core/rules/mandatory/unique_group_ids.py
turvallisuusneuvonta/csaf/core/rules/mandatory/unique_product_ids.py
turvallisuusneuvonta/csaf/core/rules/mandatory/valid_category_name.py
turvallisuusneuvonta/csaf/cvss/__init__.py
turvallisuusneuvonta/csaf/cvss/cvss.py
turvallisuusneuvonta/csaf/cvss/definitions.py
turvallisuusneuvonta-2025.10.2.dist-info/licenses/LICENSE
turvallisuusneuvonta-2025.10.2.dist-info/METADATA
turvallisuusneuvonta-2025.10.2.dist-info/WHEEL
turvallisuusneuvonta-2025.10.2.dist-info/entry_points.txt
turvallisuusneuvonta-2025.10.2.dist-info/top_level.txt
turvallisuusneuvonta-2025.10.2.dist-info/RECORD
