Metadata-Version: 2.4
Name: turvallisuusneuvonta
Version: 2025.10.2
Summary: Security advisory (Finnish: turvallisuusneuvonta) audit tool.
Author-email: Stefan Hagen <stefan@hagen.link>
Maintainer-email: Stefan Hagen <stefan@hagen.link>
License-Expression: MIT
Project-URL: Homepage, https://git.sr.ht/~sthagen/turvallisuusneuvonta
Project-URL: Bug-Tracker, https://todo.sr.ht/~sthagen/turvallisuusneuvonta
Project-URL: Documentation, https://codes.dilettant.life/docs/turvallisuusneuvonta
Project-URL: Source-Code, https://git.sr.ht/~sthagen/turvallisuusneuvonta
Project-URL: Test-Coverage, https://codes.dilettant.life/coverage/turvallisuusneuvonta
Keywords: csaf,developer-tools,validation,verification
Classifier: Development Status :: 3 - Alpha
Classifier: Intended Audience :: Developers
Classifier: Programming Language :: Python :: 3.10
Classifier: Programming Language :: Python :: 3.11
Classifier: Programming Language :: Python :: 3.12
Classifier: Programming Language :: Python :: 3.13
Classifier: Programming Language :: Python :: 3.9
Requires-Python: >=3.9
License-File: LICENSE
Requires-Dist: jmespath>=1.0.1
Requires-Dist: langcodes>=3.5.0
Requires-Dist: lazr.uri>=1.0.7
Requires-Dist: msgspec>=0.18.6
Requires-Dist: pydantic>=2.10.3
Requires-Dist: typer>=0.15.1
Provides-Extra: dev
Requires-Dist: black; extra == "dev"
Requires-Dist: coverage; extra == "dev"
Requires-Dist: hypothesis; extra == "dev"
Requires-Dist: mypy; extra == "dev"
Requires-Dist: pytest; extra == "dev"
Requires-Dist: pytest-cov; extra == "dev"
Requires-Dist: pytest-flake8; extra == "dev"
Requires-Dist: ruff; extra == "dev"
Dynamic: license-file
